src/__init__.py
src/client.py
src/constants.py
src/options.py
src/sdk.py
src/utils.py
src/validation.py
src/model/execution_result.py
src/model/identifier_prop_names.py
src/model/identifying_properties.py
src/model/payload.py
src/model/queue_item.py
src/model/round.py
src/processor/batch_processor.py
src/transporter/http_transporter.py
earnalliance_python-1.0.1.dist-info/METADATA
earnalliance_python-1.0.1.dist-info/WHEEL
earnalliance_python-1.0.1.dist-info/licenses/LICENSE
earnalliance_python-1.0.1.dist-info/RECORD
