Metadata-Version: 2.1
Name: earnalliance-python
Version: 1.0.1
Summary: Earn Alliance python SDK
License-File: LICENSE
Classifier: License :: OSI Approved :: MIT License
Classifier: Operating System :: OS Independent
Classifier: Programming Language :: Python :: 3
Requires-Python: >=3.11
